pyexceptions/__init__.py
pyexceptions/exceprion_reporter.py
pyexceptions/jinja_changes.py
pyexceptions/multi_value_dict.py
pyexceptions/safe_exception_handler.py
pyexceptions/templates/500-production.html
pyexceptions/templates/500.html
py_exceptions-1.2.2.dist-info/LICENSE.md
py_exceptions-1.2.2.dist-info/METADATA
py_exceptions-1.2.2.dist-info/WHEEL
py_exceptions-1.2.2.dist-info/top_level.txt
py_exceptions-1.2.2.dist-info/RECORD
