Metadata-Version: 2.1
Name: py-exceptions
Version: 1.2.2
Summary: A simple python exception reporter
Home-page: https://github.com/PotatoHD404/py-exceptions
Author: PotatoHD404
License: MIT
Keywords: py-exceptions
Platform: UNKNOWN
Classifier: Development Status :: 3 - Alpha
Classifier: Intended Audience :: Developers
Classifier: License :: OSI Approved :: MIT License
Classifier: Programming Language :: Python :: 3.8
Classifier: Programming Language :: Python :: 3.9
Classifier: Topic :: Software Development :: Libraries :: Python Modules
